{
  "format_version": "1.21.6",
  "credit": "Made with Blockbench",
  "textures": {
    "0": "custom/tools/crime/ammo/46mm_casing",
    "particle": "custom/tools/crime/ammo/46mm_casing"
  },
  "elements": [
    {
      "from": [
        7.5,
        7.5,
        7.5
      ],
      "to": [
        8.7,
        7.8,
        8.01
      ],
      "rotation": {
        "angle": 45,
        "axis": "y",
        "origin": [
          8.1,
          11.36,
          7.755
        ]
      },
      "faces": {
        "north": {
          "uv": [
            2,
            9,
            3,
            9.5
          ],
          "texture": "#0"
        },
        "east": {
          "uv": [
            8,
            12,
            8.5,
            12.5
          ],
          "texture": "#0"
        },
        "south": {
          "uv": [
            9,
            2,
            10,
            2.5
          ],
          "texture": "#0"
        },
        "west": {
          "uv": [
            12,
            8,
            12.5,
            8.5
          ],
          "texture": "#0"
        },
        "up": {
          "uv": [
            4,
            9.5,
            3,
            9
          ],
          "texture": "#0"
        },
        "down": {
          "uv": [
            10,
            3,
            9,
            3.5
          ],
          "texture": "#0"
        }
      }
    },
    {
      "from": [
        7.5,
        7.5,
        7.5
      ],
      "to": [
        8.7,
        7.8,
        8.01
      ],
      "rotation": {
        "angle": 0,
        "axis": "y",
        "origin": [
          8.1,
          11.06495,
          7.755
        ]
      },
      "faces": {
        "north": {
          "uv": [
            4,
            9,
            5,
            9.5
          ],
          "texture": "#0"
        },
        "east": {
          "uv": [
            9,
            12,
            9.5,
            12.5
          ],
          "texture": "#0"
        },
        "south": {
          "uv": [
            9,
            4,
            10,
            4.5
          ],
          "texture": "#0"
        },
        "west": {
          "uv": [
            12,
            9,
            12.5,
            9.5
          ],
          "texture": "#0"
        },
        "up": {
          "uv": [
            10,
            5.5,
            9,
            5
          ],
          "texture": "#0"
        },
        "down": {
          "uv": [
            7,
            9,
            6,
            9.5
          ],
          "texture": "#0"
        }
      }
    },
    {
      "from": [
        7.6,
        7.8,
        7.55
      ],
      "to": [
        8.6,
        8.1,
        7.96
      ],
      "rotation": {
        "angle": 0,
        "axis": "y",
        "origin": [
          8.1,
          11.06495,
          7.755
        ]
      },
      "faces": {
        "north": {
          "uv": [
            11,
            0,
            12,
            0.5
          ],
          "texture": "#0"
        },
        "east": {
          "uv": [
            13,
            3,
            13.5,
            3.5
          ],
          "texture": "#0"
        },
        "south": {
          "uv": [
            1,
            11,
            2,
            11.5
          ],
          "texture": "#0"
        },
        "west": {
          "uv": [
            4,
            13,
            4.5,
            13.5
          ],
          "texture": "#0"
        },
        "up": {
          "uv": [
            12,
            1.5,
            11,
            1
          ],
          "texture": "#0"
        },
        "down": {
          "uv": [
            3,
            11,
            2,
            11.5
          ],
          "texture": "#0"
        }
      }
    },
    {
      "from": [
        7.6,
        7.8,
        7.55
      ],
      "to": [
        8.6,
        8.1,
        7.96
      ],
      "rotation": {
        "angle": 45,
        "axis": "y",
        "origin": [
          8.1,
          11.36,
          7.755
        ]
      },
      "faces": {
        "north": {
          "uv": [
            11,
            2,
            12,
            2.5
          ],
          "texture": "#0"
        },
        "east": {
          "uv": [
            13,
            4,
            13.5,
            4.5
          ],
          "texture": "#0"
        },
        "south": {
          "uv": [
            3,
            11,
            4,
            11.5
          ],
          "texture": "#0"
        },
        "west": {
          "uv": [
            5,
            13,
            5.5,
            13.5
          ],
          "texture": "#0"
        },
        "up": {
          "uv": [
            12,
            3.5,
            11,
            3
          ],
          "texture": "#0"
        },
        "down": {
          "uv": [
            5,
            11,
            4,
            11.5
          ],
          "texture": "#0"
        }
      }
    },
    {
      "from": [
        8.175,
        9.6,
        7.475
      ],
      "to": [
        8.7,
        10.4,
        8.035
      ],
      "rotation": {
        "angle": 15,
        "axis": "z",
        "origin": [
          8.7,
          9.6,
          7.5
        ]
      },
      "faces": {
        "north": {
          "uv": [
            3,
            10,
            3.5,
            11
          ],
          "texture": "#0"
        },
        "east": {
          "uv": [
            10,
            3,
            10.5,
            4
          ],
          "texture": "#0"
        },
        "south": {
          "uv": [
            4,
            10,
            4.5,
            11
          ],
          "texture": "#0"
        },
        "west": {
          "uv": [
            10,
            4,
            10.5,
            5
          ],
          "texture": "#0"
        },
        "up": {
          "uv": [
            12.5,
            12.5,
            12,
            12
          ],
          "texture": "#0"
        },
        "down": {
          "uv": [
            0.5,
            13,
            0,
            13.5
          ],
          "texture": "#0"
        }
      }
    },
    {
      "from": [
        7.5,
        9.6,
        7.475
      ],
      "to": [
        7.925,
        10.4,
        8.035
      ],
      "rotation": {
        "angle": -15,
        "axis": "z",
        "origin": [
          7.5,
          9.6,
          7.5
        ]
      },
      "faces": {
        "north": {
          "uv": [
            10,
            0,
            10.5,
            1
          ],
          "texture": "#0"
        },
        "east": {
          "uv": [
            10,
            1,
            10.5,
            2
          ],
          "texture": "#0"
        },
        "south": {
          "uv": [
            2,
            10,
            2.5,
            11
          ],
          "texture": "#0"
        },
        "west": {
          "uv": [
            10,
            2,
            10.5,
            3
          ],
          "texture": "#0"
        },
        "up": {
          "uv": [
            11.5,
            12.5,
            11,
            12
          ],
          "texture": "#0"
        },
        "down": {
          "uv": [
            12.5,
            11,
            12,
            11.5
          ],
          "texture": "#0"
        }
      }
    },
    {
      "from": [
        7.82,
        9.41285,
        8.07656
      ],
      "to": [
        8.38,
        10.21285,
        8.57656
      ],
      "rotation": {
        "angle": -15,
        "axis": "x",
        "origin": [
          8.1,
          8.66495,
          7.755
        ]
      },
      "faces": {
        "north": {
          "uv": [
            5,
            10,
            5.5,
            11
          ],
          "texture": "#0"
        },
        "east": {
          "uv": [
            10,
            5,
            10.5,
            6
          ],
          "texture": "#0"
        },
        "south": {
          "uv": [
            6,
            10,
            6.5,
            11
          ],
          "texture": "#0"
        },
        "west": {
          "uv": [
            10,
            6,
            10.5,
            7
          ],
          "texture": "#0"
        },
        "up": {
          "uv": [
            13.5,
            0.5,
            13,
            0
          ],
          "texture": "#0"
        },
        "down": {
          "uv": [
            1.5,
            13,
            1,
            13.5
          ],
          "texture": "#0"
        }
      }
    },
    {
      "from": [
        7.82,
        9.41285,
        6.93344
      ],
      "to": [
        8.38,
        10.21285,
        7.48344
      ],
      "rotation": {
        "angle": 15,
        "axis": "x",
        "origin": [
          8.1,
          8.66495,
          7.755
        ]
      },
      "faces": {
        "north": {
          "uv": [
            7,
            10,
            7.5,
            11
          ],
          "texture": "#0"
        },
        "east": {
          "uv": [
            10,
            7,
            10.5,
            8
          ],
          "texture": "#0"
        },
        "south": {
          "uv": [
            8,
            10,
            8.5,
            11
          ],
          "texture": "#0"
        },
        "west": {
          "uv": [
            10,
            8,
            10.5,
            9
          ],
          "texture": "#0"
        },
        "up": {
          "uv": [
            13.5,
            1.5,
            13,
            1
          ],
          "texture": "#0"
        },
        "down": {
          "uv": [
            2.5,
            13,
            2,
            13.5
          ],
          "texture": "#0"
        }
      }
    },
    {
      "from": [
        7.845,
        7.5,
        7.155
      ],
      "to": [
        8.355,
        7.8,
        8.355
      ],
      "rotation": {
        "angle": 0,
        "axis": "y",
        "origin": [
          8.1,
          11.06495,
          7.755
        ]
      },
      "faces": {
        "north": {
          "uv": [
            13,
            2,
            13.5,
            2.5
          ],
          "texture": "#0"
        },
        "east": {
          "uv": [
            9,
            10,
            10,
            10.5
          ],
          "texture": "#0"
        },
        "south": {
          "uv": [
            3,
            13,
            3.5,
            13.5
          ],
          "texture": "#0"
        },
        "west": {
          "uv": [
            10,
            9,
            11,
            9.5
          ],
          "texture": "#0"
        },
        "up": {
          "uv": [
            10.5,
            11,
            10,
            10
          ],
          "texture": "#0"
        },
        "down": {
          "uv": [
            0.5,
            11,
            0,
            12
          ],
          "texture": "#0"
        }
      }
    },
    {
      "from": [
        7.895,
        7.8,
        7.255
      ],
      "to": [
        8.305,
        8.1,
        8.255
      ],
      "rotation": {
        "angle": 0,
        "axis": "y",
        "origin": [
          8.1,
          11.06495,
          7.755
        ]
      },
      "faces": {
        "north": {
          "uv": [
            13,
            5,
            13.5,
            5.5
          ],
          "texture": "#0"
        },
        "east": {
          "uv": [
            11,
            4,
            12,
            4.5
          ],
          "texture": "#0"
        },
        "south": {
          "uv": [
            6,
            13,
            6.5,
            13.5
          ],
          "texture": "#0"
        },
        "west": {
          "uv": [
            5,
            11,
            6,
            11.5
          ],
          "texture": "#0"
        },
        "up": {
          "uv": [
            11.5,
            6,
            11,
            5
          ],
          "texture": "#0"
        },
        "down": {
          "uv": [
            6.5,
            11,
            6,
            12
          ],
          "texture": "#0"
        }
      }
    },
    {
      "from": [
        7.845,
        7.5,
        7.155
      ],
      "to": [
        8.355,
        7.8,
        8.355
      ],
      "rotation": {
        "angle": 45,
        "axis": "y",
        "origin": [
          8.1,
          11.36,
          7.755
        ]
      },
      "faces": {
        "north": {
          "uv": [
            10,
            12,
            10.5,
            12.5
          ],
          "texture": "#0"
        },
        "east": {
          "uv": [
            9,
            6,
            10,
            6.5
          ],
          "texture": "#0"
        },
        "south": {
          "uv": [
            12,
            10,
            12.5,
            10.5
          ],
          "texture": "#0"
        },
        "west": {
          "uv": [
            9,
            7,
            10,
            7.5
          ],
          "texture": "#0"
        },
        "up": {
          "uv": [
            9.5,
            9,
            9,
            8
          ],
          "texture": "#0"
        },
        "down": {
          "uv": [
            9.5,
            9,
            9,
            10
          ],
          "texture": "#0"
        }
      }
    },
    {
      "from": [
        7.895,
        7.8,
        7.255
      ],
      "to": [
        8.305,
        8.1,
        8.255
      ],
      "rotation": {
        "angle": 45,
        "axis": "y",
        "origin": [
          8.1,
          11.36,
          7.755
        ]
      },
      "faces": {
        "north": {
          "uv": [
            13,
            6,
            13.5,
            6.5
          ],
          "texture": "#0"
        },
        "east": {
          "uv": [
            11,
            6,
            12,
            6.5
          ],
          "texture": "#0"
        },
        "south": {
          "uv": [
            7,
            13,
            7.5,
            13.5
          ],
          "texture": "#0"
        },
        "west": {
          "uv": [
            7,
            11,
            8,
            11.5
          ],
          "texture": "#0"
        },
        "up": {
          "uv": [
            11.5,
            8,
            11,
            7
          ],
          "texture": "#0"
        },
        "down": {
          "uv": [
            8.5,
            11,
            8,
            12
          ],
          "texture": "#0"
        }
      }
    },
    {
      "from": [
        7.5,
        8.1,
        7.5
      ],
      "to": [
        8.7,
        9.6,
        8.01
      ],
      "rotation": {
        "angle": 45,
        "axis": "y",
        "origin": [
          8.1,
          9.86,
          7.755
        ]
      },
      "faces": {
        "north": {
          "uv": [
            0,
            0,
            1,
            2.5
          ],
          "texture": "#0"
        },
        "east": {
          "uv": [
            4,
            4,
            4.5,
            6.5
          ],
          "texture": "#0"
        },
        "south": {
          "uv": [
            1,
            0,
            2,
            2.5
          ],
          "texture": "#0"
        },
        "west": {
          "uv": [
            5,
            0,
            5.5,
            2.5
          ],
          "texture": "#0"
        },
        "up": {
          "uv": [
            12,
            8.5,
            11,
            8
          ],
          "texture": "#0"
        },
        "down": {
          "uv": [
            10,
            11,
            9,
            11.5
          ],
          "texture": "#0"
        }
      }
    },
    {
      "from": [
        7.845,
        8.1,
        7.155
      ],
      "to": [
        8.355,
        9.6,
        8.355
      ],
      "rotation": {
        "angle": 0,
        "axis": "y",
        "origin": [
          8.1,
          9.56495,
          7.755
        ]
      },
      "faces": {
        "north": {
          "uv": [
            5,
            3,
            5.5,
            5.5
          ],
          "texture": "#0"
        },
        "east": {
          "uv": [
            2,
            0,
            3,
            2.5
          ],
          "texture": "#0"
        },
        "south": {
          "uv": [
            0,
            6,
            0.5,
            8.5
          ],
          "texture": "#0"
        },
        "west": {
          "uv": [
            0,
            3,
            1,
            5.5
          ],
          "texture": "#0"
        },
        "up": {
          "uv": [
            11.5,
            10,
            11,
            9
          ],
          "texture": "#0"
        },
        "down": {
          "uv": [
            10.5,
            11,
            10,
            12
          ],
          "texture": "#0"
        }
      }
    },
    {
      "from": [
        7.5,
        8.1,
        7.5
      ],
      "to": [
        8.7,
        9.6,
        8.01
      ],
      "rotation": {
        "angle": 0,
        "axis": "y",
        "origin": [
          8.1,
          9.56495,
          7.755
        ]
      },
      "faces": {
        "north": {
          "uv": [
            3,
            0,
            4,
            2.5
          ],
          "texture": "#0"
        },
        "east": {
          "uv": [
            6,
            0,
            6.5,
            2.5
          ],
          "texture": "#0"
        },
        "south": {
          "uv": [
            1,
            3,
            2,
            5.5
          ],
          "texture": "#0"
        },
        "west": {
          "uv": [
            1,
            6,
            1.5,
            8.5
          ],
          "texture": "#0"
        },
        "up": {
          "uv": [
            12,
            10.5,
            11,
            10
          ],
          "texture": "#0"
        },
        "down": {
          "uv": [
            12,
            11,
            11,
            11.5
          ],
          "texture": "#0"
        }
      }
    },
    {
      "from": [
        7.845,
        8.1,
        7.155
      ],
      "to": [
        8.355,
        9.6,
        8.355
      ],
      "rotation": {
        "angle": 45,
        "axis": "y",
        "origin": [
          8.1,
          9.86,
          7.755
        ]
      },
      "faces": {
        "north": {
          "uv": [
            2,
            6,
            2.5,
            8.5
          ],
          "texture": "#0"
        },
        "east": {
          "uv": [
            2,
            3,
            3,
            5.5
          ],
          "texture": "#0"
        },
        "south": {
          "uv": [
            3,
            6,
            3.5,
            8.5
          ],
          "texture": "#0"
        },
        "west": {
          "uv": [
            3,
            3,
            4,
            5.5
          ],
          "texture": "#0"
        },
        "up": {
          "uv": [
            0.5,
            13,
            0,
            12
          ],
          "texture": "#0"
        },
        "down": {
          "uv": [
            12.5,
            0,
            12,
            1
          ],
          "texture": "#0"
        }
      }
    }
  ],
  "display": {
    "thirdperson_righthand": {
      "rotation": [
        0,
        0,
        1
      ],
      "translation": [
        0,
        -1,
        0.25
      ],
      "scale": [
        0.5,
        0.5,
        0.5
      ]
    },
    "thirdperson_lefthand": {
      "translation": [
        0,
        -1.25,
        0.25
      ],
      "scale": [
        0.5,
        0.5,
        0.5
      ]
    },
    "firstperson_righthand": {
      "translation": [
        4.25,
        -1.5,
        0
      ]
    },
    "firstperson_lefthand": {
      "translation": [
        4.5,
        -1.75,
        0
      ]
    },
    "ground": {
      "rotation": [
        90,
        0,
        0
      ]
    },
    "gui": {
      "rotation": [
        0,
        31,
        -16
      ],
      "translation": [
        -0.75,
        -4,
        0
      ],
      "scale": [
        1.3,
        1.3,
        1.3
      ]
    },
    "head": {
      "scale": [
        0,
        0,
        0
      ]
    },
    "fixed": {
      "translation": [
        0,
        -5,
        0
      ],
      "scale": [
        2,
        2,
        2
      ]
    },
    "on_shelf": {
      "translation": [
        1.5,
        -2.25,
        0
      ],
      "scale": [
        2,
        2,
        2
      ]
    }
  }
}
